macnotesapp/__init__.py
macnotesapp/__main__.py
macnotesapp/_version.py
macnotesapp/logging.py
macnotesapp/macnotesapp.applescript
macnotesapp/macnotesapp_applescript.py
macnotesapp/notesapp.py
macnotesapp/script_loader.py
macnotesapp/utils.py
macnotesapp/cli/__init__.py
macnotesapp/cli/cli.py
macnotesapp/cli/cli_config.py
macnotesapp/cli/cli_help.py
macnotesapp/cli/cli_param_types.py
macnotesapp/cli/click_rich_echo.py
macnotesapp/cli/readable.py
macnotesapp-0.8.2.dist-info/METADATA
macnotesapp-0.8.2.dist-info/WHEEL
macnotesapp-0.8.2.dist-info/entry_points.txt
macnotesapp-0.8.2.dist-info/licenses/LICENSE
macnotesapp-0.8.2.dist-info/RECORD
