Metadata-Version: 2.4
Name: macnotesapp
Version: 0.8.2
Summary: Work with Apple MacOS Notes.app from the command line. Also includes python interface for scripting Notes.app from your own python code.
Project-URL: Homepage, https://github.com/RhetTbull/macnotesapp
Project-URL: Repository, https://github.com/RhetTbull/macnotesapp
Author-email: Rhet Turnbull <rturnbull@gmail.com>
License-Expression: MIT
License-File: LICENSE
Keywords: cli,mac,macos
Requires-Python: <3.14,>=3.10
Requires-Dist: click<9.0.0,>=8.1.2
Requires-Dist: lxml-html-clean>=0.1.1
Requires-Dist: lxml<6.0.0,>=5.2.1
Requires-Dist: markdown2<3.0.0,>=2.4.3
Requires-Dist: markdownify<1.0.0,>=0.11.6
Requires-Dist: py-applescript<2.0.0,>=1.0.3
Requires-Dist: pyobjc-framework-scriptingbridge>=9.0.1
Requires-Dist: questionary<=3.0.0,>=1.10.0
Requires-Dist: readability-lxml<0.9.0,>=0.8.2
Requires-Dist: requests<3.0.0,>=2.28.1
Requires-Dist: rich<=14.0.0,>=12.4.4
Requires-Dist: toml<0.11.0,>=0.10.2
Requires-Dist: validators<1.0.0,>=0.20.0
Requires-Dist: wheel>=0.37.1
Requires-Dist: xdg-base-dirs>=6.0.0
